{"cameraMode":{"drawMode":0,"name":"Shaded","section":"Shading Mode"},"sceneLighting":true,"audioPlay":false,"sceneViewState":{"showFog":false,"showMaterialUpdate":false,"showSkybox":true,"showFlares":true,"showImageEffects":true,"showParticleSystems":true,"showVisualEffectGraphs":true,"m_FxEnabled":true},"in2DMode":false,"pivot":{"x":-144.8253173828125,"y":-103.9408187866211,"z":595.8717651367188},"rotation":{"x":0.13118967413902284,"y":-0.17792128026485444,"z":0.02432606928050518,"w":0.9750837683677673},"size":262.4274597167969,"orthographic":false}